{
    "all" : {
        "source" : {
          "tracking" : {
            "hdfs-src" : "/production/source/tracking/",
            "remote" : "root@10.0.0.147:/root/backup/hdfs/production/source/tracking/"
          },

          "comments" : {
            "hdfs-src" : "/production/source/comments",
            "remote" : "root@10.0.0.147:/root/backup/hdfs/production/source/comments"
          }
        },

        "datas" : {
          "hdfs-src" : "/production/datas/",
          "remote" : "root@10.0.0.147:/root/backup/hdfs/production/datas",
        },


        "app" : {
          "hdfs-src" : "/production/app/",
          "remote" : "root@10.0.0.147:/root/backup/hdfs/production/app"
        },


        "interaction" : {
          "hdfs-src" : "/production/interaction/",
          "remote" : "root@10.0.0.147:/root/backup/hdfs/production/interaction"
        },

        "exceptions" : {
            "hdfs-src" : "/production/exceptions/",
            "remote" : "root@10.0.0.147:/root/backup/hdfs/production/exceptions"
        },

        "opjobs" : {
          "hdfs-src" : "/production/opjobs",
          "remote" : "root@10.0.0.147:/root/backup/hdfs/production/opjobs/"
        }
}
